<?xml version="1.0" encoding="UTF-8"?>
<objects serializationModel="Studio.02.02.00">
	<object class="AudioFile" id="{d186d99d-88de-4008-8560-4e991708baaa}">
		<property name="assetPath">
			<value>Announcer/Begin/announcer_0002_e.wav</value>
		</property>
		<property name="frequencyInKHz">
			<value>11.0249996</value>
		</property>
		<property name="channelCount">
			<value>2</value>
		</property>
		<property name="length">
			<value>3.1146485260770973</value>
		</property>
		<relationship name="masterAssetFolder">
			<destination>{e87ba75f-f1c2-46f3-b796-568cb847176a}</destination>
		</relationship>
	</object>
</objects>
